{
	"format_version": "1.21.6",
	"credit": "Made with Blockbench",
	"parent": "block/block",
	"render_type": "cutout",
	"textures": {
		"1": "occultism:block/pedestal_base",
		"particle": "occultism:block/otherstone"
	},
	"elements": [
		{
			"from": [3, 3, 3],
			"to": [13, 14, 13],
			"rotation": {"angle": 0, "axis": "y", "origin": [7, -1, 7]},
			"faces": {
				"north": {"uv": [0, 0, 5, 5.5], "texture": "#1"},
				"east": {"uv": [0, 0, 5, 5.5], "texture": "#1"},
				"south": {"uv": [0, 0, 5, 5.5], "texture": "#1"},
				"west": {"uv": [0, 0, 5, 5.5], "texture": "#1"},
				"up": {"uv": [0, 0, 10, 10], "texture": "#1"},
				"down": {"uv": [0, 0, 10, 10], "texture": "#1"}
			}
		},
		{
			"from": [2, 14, 2],
			"to": [14, 16, 14],
			"rotation": {"angle": 0, "axis": "y", "origin": [7, 1, 7]},
			"faces": {
				"north": {"uv": [0, 6, 6, 7], "texture": "#1"},
				"east": {"uv": [0, 6, 6, 7], "texture": "#1"},
				"south": {"uv": [0, 6, 6, 7], "texture": "#1"},
				"west": {"uv": [0, 6, 6, 7], "texture": "#1"},
				"up": {"uv": [1, 9, 7, 15], "texture": "#1"},
				"down": {"uv": [10, 1, 15, 6], "texture": "#1"}
			}
		},
		{
			"from": [2, 1, 2],
			"to": [14, 3, 14],
			"rotation": {"angle": 0, "axis": "y", "origin": [7, -12, 7]},
			"faces": {
				"north": {"uv": [0, 6, 6, 7], "texture": "#1"},
				"east": {"uv": [0, 6, 6, 7], "texture": "#1"},
				"south": {"uv": [0, 6, 6, 7], "texture": "#1"},
				"west": {"uv": [0, 6, 6, 7], "texture": "#1"},
				"up": {"uv": [9.5, 0.5, 15.5, 6.5], "texture": "#1"},
				"down": {"uv": [0, 0, 12, 12], "texture": "#1"}
			}
		},
		{
			"from": [1, 0, 1],
			"to": [15, 2, 15],
			"rotation": {"angle": 0, "axis": "y", "origin": [7, -13, 7]},
			"faces": {
				"north": {"uv": [0, 7, 7, 8], "texture": "#1"},
				"east": {"uv": [0, 7, 7, 8], "texture": "#1"},
				"south": {"uv": [0, 7, 7, 8], "texture": "#1"},
				"west": {"uv": [0, 7, 7, 8], "texture": "#1"},
				"up": {"uv": [9, 0, 16, 7], "texture": "#1"},
				"down": {"uv": [10, 1, 15, 6], "texture": "#1"}
			}
		},
		{
			"from": [-6, 0, 8],
			"to": [2, 16, 8.05],
			"rotation": {"angle": -45, "axis": "y", "origin": [8, 8, 8]},
			"faces": {
				"north": {"uv": [11.5, 7, 16, 16], "texture": "#1"},
				"east": {"uv": [5.5, 2.5, 6.5, 3.5], "texture": "#1"},
				"south": {"uv": [16, 7, 11.5, 16], "texture": "#1"},
				"west": {"uv": [5.5, 2.5, 6.5, 3.5], "texture": "#1"},
				"up": {"uv": [5.5, 2.5, 6.5, 3.5], "texture": "#1"},
				"down": {"uv": [5.5, 2.5, 6.5, 3.5], "texture": "#1"}
			}
		},
		{
			"from": [14, 0, 8],
			"to": [22, 16, 8.05],
			"rotation": {"angle": 45, "axis": "y", "origin": [8, 8, 8]},
			"faces": {
				"north": {"uv": [16, 7, 11.5, 16], "texture": "#1"},
				"east": {"uv": [6.5, 2.5, 5.5, 3.5], "texture": "#1"},
				"south": {"uv": [11.5, 7, 16, 16], "texture": "#1"},
				"west": {"uv": [6.5, 2.5, 5.5, 3.5], "texture": "#1"},
				"up": {"uv": [6.5, 2.5, 5.5, 3.5], "texture": "#1"},
				"down": {"uv": [6.5, 2.5, 5.5, 3.5], "texture": "#1"}
			}
		},
		{
			"from": [14, 0, 7.95],
			"to": [22, 16, 8],
			"rotation": {"angle": -45, "axis": "y", "origin": [8, 8, 8]},
			"faces": {
				"north": {"uv": [16, 7, 11.5, 16], "texture": "#1"},
				"east": {"uv": [5.5, 2.5, 6.5, 3.5], "texture": "#1"},
				"south": {"uv": [11.5, 7, 16, 16], "texture": "#1"},
				"west": {"uv": [5.5, 2.5, 6.5, 3.5], "texture": "#1"},
				"up": {"uv": [6.5, 3.5, 5.5, 2.5], "texture": "#1"},
				"down": {"uv": [6.5, 3.5, 5.5, 2.5], "texture": "#1"}
			}
		},
		{
			"from": [-6, 0, 7.95],
			"to": [2, 16, 8],
			"rotation": {"angle": 45, "axis": "y", "origin": [8, 8, 8]},
			"faces": {
				"north": {"uv": [11.5, 7, 16, 16], "texture": "#1"},
				"east": {"uv": [6.5, 2.5, 5.5, 3.5], "texture": "#1"},
				"south": {"uv": [16, 7, 11.5, 16], "texture": "#1"},
				"west": {"uv": [6.5, 2.5, 5.5, 3.5], "texture": "#1"},
				"up": {"uv": [5.5, 3.5, 6.5, 2.5], "texture": "#1"},
				"down": {"uv": [5.5, 3.5, 6.5, 2.5], "texture": "#1"}
			}
		}
	],
	"display": {
		"thirdperson_righthand": {
			"rotation": [75, 45, 0],
			"translation": [0, 2.5, 0],
			"scale": [0.375, 0.375, 0.375]
		},
		"thirdperson_lefthand": {
			"rotation": [75, 45, 0],
			"translation": [0, 2.5, 0],
			"scale": [0.375, 0.375, 0.375]
		},
		"firstperson_righthand": {
			"rotation": [0, 45, 0],
			"scale": [0.4, 0.4, 0.4]
		},
		"firstperson_lefthand": {
			"rotation": [0, -135, 0],
			"scale": [0.4, 0.4, 0.4]
		},
		"ground": {
			"translation": [0, 3, 0],
			"scale": [0.25, 0.25, 0.25]
		},
		"gui": {
			"rotation": [30, -135, 0],
			"scale": [0.6, 0.6, 0.6]
		},
		"fixed": {
			"scale": [0.5, 0.5, 0.5]
		}
	},
	"groups": [
		{
			"name": "group",
			"origin": [8.78805, 8, 9.21698],
			"color": 0,
			"children": []
		},
		0,
		1,
		2,
		3,
		4,
		5,
		6,
		7
	]
}